validate/__init__.py
validate/validate_cpf.py
devopsvalidatecpf-0.0.4.dist-info/METADATA
devopsvalidatecpf-0.0.4.dist-info/WHEEL
devopsvalidatecpf-0.0.4.dist-info/top_level.txt
devopsvalidatecpf-0.0.4.dist-info/RECORD
